dirstruct/__about__.py
dirstruct/__init__.py
dirstruct/_diff_paths.py
dirstruct/_diff_strings.py
dirstruct/_show.py
dirstruct/_temp_tree.py
dirstruct-0.3.0.dist-info/METADATA
dirstruct-0.3.0.dist-info/WHEEL
dirstruct-0.3.0.dist-info/top_level.txt
dirstruct-0.3.0.dist-info/RECORD
