Metadata-Version: 2.1
Name: dirstruct
Version: 0.3.0
Summary: Tools for directory structures
Author-email: Nico Schlömer <nico.schloemer@gmail.com>
Project-URL: Homepage, https://github.com/nschloe/dirstruct
Project-URL: Issues, https://github.com/nschloe/dirstruct/issues
Classifier: Development Status :: 3 - Alpha
Classifier: License :: Other/Proprietary License
Classifier: Operating System :: OS Independent
Classifier: Programming Language :: Python
Classifier: Programming Language :: Python :: 3
Classifier: Programming Language :: Python :: 3.7
Classifier: Programming Language :: Python :: 3.8
Classifier: Programming Language :: Python :: 3.9
Classifier: Programming Language :: Python :: 3.10
Classifier: Programming Language :: Python :: 3.11
Classifier: Topic :: Utilities
Requires-Python: >=3.7
Requires-Dist: rich
